{
    "1": [
        "Maya_Soetoro-Ng",
        "Edward_Snowden",
        "Lolo_Soetoro",
        "Barack_Obama_Sr.",
        "Sheila_Miyoshi_Jager",
        "George_Zimmerman",
        "Laurence_Tribe",
        "Jeremiah_Wright",
        "Jeffrey_Goldberg"
    ],
    "2": [
        "Anwar_al-Awlaki",
        "Osama_bin_Laden"
    ],
    "3": [
        "Bruce_Springsteen",
        "Pope_Francis"
    ],
    "4": [
        "Stanley_Armour_Dunham",
        "Ann_Dunham",
        "Madelyn_Dunham"
    ],
    "5": [
        "Tony_Rezko",
        "Gautama_Buddha"
    ],
    "6": [
        "HIV"
    ],
    "7": [
        "Barack_Obama",
        "John_McCain",
        "Tim_Kaine",
        "Joe_Biden",
        "Jimmy_Carter",
        "Sarah_Palin",
        "Bill_Clinton",
        "Mitt_Romney",
        "Dick_Cheney",
        "Calvin_Coolidge",
        "Hillary_Clinton",
        "Donald_Trump"
    ],
    "8": [
        "Muammar_Gaddafi",
        "Nelson_Mandela",
        "Margaret_Thatcher"
    ],
    "9": [
        "Jefferson_Davis",
        "Benjamin_Franklin",
        "Ronald_Reagan",
        "Robert_F._Kennedy",
        "Abraham_Lincoln",
        "Ted_Kennedy",
        "Dwight_D._Eisenhower"
    ],
    "10": [
        "Anthony_Albanese",
        "Vladimir_Putin",
        "Dmitry_Medvedev",
        "David_Petraeus",
        "Benjamin_Netanyahu",
        "Mahmoud_Abbas",
        "Ra\u00fal_Castro"
    ],
    "11": [
        "Paul_Ryan",
        "Tom_Carper",
        "Elena_Kagan",
        "Alan_Keyes",
        "Michelle_Obama",
        "Ken_Salazar",
        "Sonia_Sotomayor",
        "Valerie_Jarrett",
        "John_Paul_Stevens",
        "Leon_Panetta",
        "Alice_Palmer_(politician)",
        "Timothy_Geithner",
        "David_Souter",
        "Carol_Moseley_Braun",
        "Evan_Bayh",
        "Peter_Fitzgerald_(politician)",
        "Tom_Coburn",
        "Ben_Bernanke"
    ],
    "12": [
        "United_Nations",
        "Arab_League"
    ],
    "13": [
        "Egypt",
        "Yemen",
        "Kenya",
        "Indonesia",
        "Australia",
        "Ethiopia",
        "Cuba",
        "Libya",
        "Somalia",
        "Syria",
        "Palestinian_National_Authority",
        "France",
        "Iraq",
        "Russia",
        "Pakistan",
        "Israel",
        "Mexico",
        "Afghanistan",
        "Iran",
        "Saudi_Arabia",
        "South_Africa"
    ],
    "14": [
        "Hawaii",
        "Indiana",
        "Delaware",
        "Missouri",
        "Virginia",
        "Kansas",
        "Illinois",
        "Massachusetts",
        "Iowa",
        "Texas",
        "Alaska",
        "Colorado"
    ],
    "15": [
        "Denver",
        "Wisconsin",
        "North_Carolina"
    ],
    "16": [
        "Abbottabad",
        "Mosul",
        "Nairobi",
        "Jakarta",
        "Baghdad",
        "Vatican_City",
        "Mexico_City",
        "Benghazi",
        "Havana",
        "Melbourne"
    ],
    "17": [
        "New_York_City",
        "Los_Angeles",
        "Chicago",
        "Seattle",
        "Honolulu",
        "Johannesburg",
        "Islamabad"
    ],
    "18": [
        "Central_Asia",
        "Crimea",
        "Molokai"
    ],
    "19": [
        "Assisi",
        "South_Jakarta",
        "Sinjar",
        "Central_Jakarta",
        "Kalorama_(Washington,_D.C.)",
        "Sochi",
        "Times_Square",
        "Menteng"
    ],
    "20": [
        "Punahou_School",
        "Calvert_School",
        "Harvard_Law_School",
        "Sidwell_Friends_School"
    ],
    "21": [
        "Columbia_University",
        "Harvard_University",
        "Northwestern_University",
        "Cairo_University",
        "Occidental_College"
    ],
    "22": [
        "Citibank",
        "New_York_Public_Interest_Research_Group",
        "Chrysler",
        "Ancestry.com",
        "General_Motors",
        "Invesco",
        "Hobby_Lobby",
        "Sidley_Austin"
    ],
    "23": [
        "Netflix"
    ],
    "24": [
        "Brookings_Institution",
        "Pew_Research_Center"
    ],
    "25": [
        "Norwegian_Nobel_Committee",
        "Fisher_House_Foundation",
        "United_Nations_Security_Council",
        "Joyce_Foundation",
        "Gamaliel_Foundation",
        "Developing_Communities_Project"
    ],
    "26": [
        "82nd_Airborne_Division",
        "United_States_Navy"
    ],
    "27": [
        "Pittsburgh_Steelers",
        "Chicago_White_Sox"
    ],
    "28": [
        "Illinois_Senate",
        "United_States_Senate"
    ],
    "29": [
        "LibriVox",
        "Project_Gutenberg"
    ],
    "30": [
        "Al_Arabiya",
        "C-SPAN"
    ],
    "31": [
        "United_States_Armed_Forces",
        "Rush_(band)"
    ],
    "32": [
        "National_Football_League"
    ],
    "33": [
        "Federal_Reserve"
    ],
    "34": [
        "Al-Qaeda",
        "Taliban"
    ],
    "35": [
        "Hamas",
        "Hezbollah",
        "Australian_Labor_Party"
    ],
    "36": [
        "Audio_Publishers_Association",
        "Gallup_(company)",
        "Fiat_Automobiles",
        "Business_International_Corporation",
        "Protestantism"
    ],
    "37": [
        "National_Security_Agency",
        "Central_Intelligence_Agency",
        "Congressional_Budget_Office",
        "Federal_Election_Commission",
        "NASA"
    ],
    "38": [
        "United_States_Secret_Service",
        "Drug_Enforcement_Administration"
    ],
    "39": [
        "United_States_Senate_Committee_on_Foreign_Relations"
    ],
    "40": [
        "Medicaid",
        "Medicare_Advantage"
    ],
    "41": [
        "Courage"
    ],
    "42": [
        "United_Nations_Security_Council_Resolution_2334"
    ],
    "43": [
        "Equal_Credit_Opportunity_Act"
    ],
    "44": [
        "Diplomatic_mission",
        "Islamic_State_of_Iraq_and_the_Levant"
    ],
    "45": [
        "Race_and_ethnicity_in_the_United_States_Census",
        "Secure_Communities",
        "Jack_Ryan",
        "Sana\u02bda",
        "Coronavirus_disease_2019"
    ],
    "46": [
        "Project_Cassandra"
    ],
    "47": [
        "Chicago_Tribune",
        "The_New_York_Times",
        "The_New_York_Times_International_Edition"
    ],
    "48": [
        "Time_(magazine)",
        "Harvard_Law_Review",
        "Money_(magazine)"
    ],
    "49": [
        "Promised_Land",
        "Arctic",
        "East_Jerusalem"
    ],
    "50": [
        "McCormick_Place",
        "Camp_David",
        "Macondo_Prospect"
    ],
    "51": [
        "Somerville_station",
        "West_Pullman_station"
    ],
    "52": [
        "The_Pentagon",
        "White_House"
    ],
    "53": [
        "Barack_Obama_Presidential_Center",
        "Altgeld_Gardens_Homes"
    ],
    "54": [
        "Shooting_of_Michael_Brown"
    ],
    "55": [
        "Civil_Rights_Act_of_1968",
        "Don't_Ask,_Don't_Tell_Repeal_Act_of_2010",
        "Antiquities_Act",
        "Religious_Freedom_Restoration_Act"
    ],
    "56": [
        "Operation_Unified_Protector",
        "Battle_of_Shiloh",
        "American_Civil_War"
    ],
    "57": [
        "Iraq_War",
        "World_War_II"
    ],
    "58": [
        "The_Holocaust",
        "Sandy_Hook_Elementary_School_shooting"
    ],
    "59": [
        "Arab_Spring",
        "Syrian_Civil_War"
    ],
    "60": [
        "Great_Recession",
        "Great_Depression"
    ],
    "61": [
        "Zionism"
    ],
    "62": [
        "Surveillance_court"
    ],
    "63": [
        "Keystone_Pipeline",
        "NJPW_The_New_Beginning"
    ],
    "64": [
        "Julian_calendar"
    ],
    "65": [
        "Grammy_Award_for_Best_Spoken_Word_Album",
        "Emmy_Award"
    ],
    "66": [
        "Nobel_Peace_Prize",
        "Nobel_Prize",
        "Academy_Awards"
    ],
    "67": [
        "Palestinians",
        "Luo_people"
    ],
    "68": [
        "START_I",
        "Trans-Pacific_Partnership"
    ],
    "69": [
        "NATO"
    ],
    "70": [
        "LGBT"
    ],
    "71": [
        "Iron_Dome",
        "Democratic_National_Convention"
    ],
    "72": [
        "International_Space_Station"
    ],
    "73": [
        "Mars"
    ],
    "74": [
        "Wailuku_River"
    ],
    "75": [
        "HuffPost"
    ],
    "76": [
        "Obama_Foundation"
    ],
    "77": [
        "18_Months"
    ],
    "78": [
        "American_Factory"
    ],
    "79": [
        "Obergefell_v._Hodges"
    ],
    "80": [
        "Hurricane_Harvey",
        "Hurricane_Irma"
    ],
    "81": [
        "Super_Bowl_XLIII",
        "1985_Chicago_Bears_season"
    ],
    "82": [
        "2014_Winter_Olympics",
        "Super_Bowl"
    ],
    "83": [
        "Cuban_thaw"
    ],
    "84": [
        "Space_Shuttle"
    ]
}